BookerPubTool/__init__.py
BookerPubTool/__main__.py
BookerPubTool/docker.py
BookerPubTool/ebook2site.py
BookerPubTool/git.py
BookerPubTool/libgen.py
BookerPubTool/npm.py
BookerPubTool/pypi.py
BookerPubTool/util.py
BookerPubTool/zhihu_msger.py
BookerPubTool/asset/__init__.py
BookerPubTool/asset/__init__.tmpl
BookerPubTool/asset/epubjs-reader.zip
BookerPubTool/asset/package.tmpl
BookerPubTool/asset/pdf.html
BookerPubTool/asset/readme.tmpl
BookerPubTool/asset/server.js
BookerPubTool/asset/server.py
BookerPubTool/asset/setup.tmpl
BookerPubTool-2023.7.9.0.dist-info/LICENSE
BookerPubTool-2023.7.9.0.dist-info/METADATA
BookerPubTool-2023.7.9.0.dist-info/WHEEL
BookerPubTool-2023.7.9.0.dist-info/entry_points.txt
BookerPubTool-2023.7.9.0.dist-info/top_level.txt
BookerPubTool-2023.7.9.0.dist-info/RECORD
